experiment_manager/__init__.py
experiment_manager/experiment_manager.py
experiment_manager/neural_net_config.py
experiment_manager/utils/__init__.py
experiment_manager/utils/dottable_config.py
experiment_manager/utils/dottable_map.py
ml_experiment_manager-0.2.9.dist-info/LICENSE
ml_experiment_manager-0.2.9.dist-info/METADATA
ml_experiment_manager-0.2.9.dist-info/WHEEL
ml_experiment_manager-0.2.9.dist-info/top_level.txt
ml_experiment_manager-0.2.9.dist-info/RECORD
