Metadata-Version: 2.1
Name: ml-experiment-manager
Version: 0.2.9
Summary: Manage data during machine learning projects
Home-page: https://github.com/paepcke/ml_experiment_manager.git
Author: Andreas Paepcke
Author-email: paepcke@cs.stanford.edu
Requires-Python: >=3.6
License-File: LICENSE
Requires-Dist: pandas (>=1.4)
Requires-Dist: numpy (>=1.19.1)
Requires-Dist: torch (>=1.7.1)
Requires-Dist: skorch (>=0.10.0)
Requires-Dist: matplotlib (>=3.3.0)
Requires-Dist: tensorboard (>=2.6.0)
Requires-Dist: tqdm (>=4.62.3)
Requires-Dist: pyarrow (>=9.0.0)
Provides-Extra: test
Requires-Dist: nose2 (>=0.9.2) ; extra == 'test'
